LICENCE.txt
MANIFEST.in
README.rst
setup.py
bin/picnic
picnic/__init__.py
picnic/picnic.py
picnic.egg-info/PKG-INFO
picnic.egg-info/SOURCES.txt
picnic.egg-info/dependency_links.txt
picnic.egg-info/top_level.txt