Metadata-Version: 1.0
Name: picnic
Version: 0.0.0.5
Summary: Python packages creation made easy
Home-page: UNKNOWN
Author: Zulko 2014
Author-email: UNKNOWN
License: see LICENSE.txt
Keywords: python module package template engine setuptools
Platform: UNKNOWN
